Metadata-Version: 2.1
Name: Flask-pyoidc
Version: 3.14.3
Summary: Flask extension for OpenID Connect authentication.
Home-page: https://github.com/zamzterz/flask-pyoidc
Author: Samuel Gulliksson
Author-email: samuel.gulliksson@gmail.com
License: Apache 2.0
License-File: LICENSE
Requires-Dist: oic ==1.6.1
Requires-Dist: Flask
Requires-Dist: requests
Requires-Dist: importlib-resources
